pyroexr-0.2.0.dist-info/METADATA
pyroexr-0.2.0.dist-info/WHEEL
pyroexr/__init__.py
pyroexr/pyroexr.pyd
pyroexr-0.2.0.dist-info/RECORD
