Metadata-Version: 2.1
Name: pyroexr
Version: 0.2.0
